asrecognition/__init__.py
asrecognition/engine.py
asrecognition-0.0.4.dist-info/LICENSE
asrecognition-0.0.4.dist-info/WHEEL
asrecognition-0.0.4.dist-info/METADATA
asrecognition-0.0.4.dist-info/RECORD
