Metadata-Version: 2.1
Name: asrecognition
Version: 0.0.4
Summary: ASRecognition: just an easy-to-use library for Automatic Speech Recognition.
Home-page: https://github.com/jonatasgrosman/asrecognition
License: MIT
Keywords: audio,speech,automatic speech recognition,asr,voice recognition,speech recognition,speech-to-text
Author: Jonatas Grosman
Author-email: jonatasgrosman@gmail.com
Maintainer: Jonatas Grosman
Maintainer-email: jonatasgrosman@gmail.com
Requires-Python: >=3.7,<3.10
Classifier: License :: OSI Approved :: MIT License
Classifier: Programming Language :: Python :: 3
Classifier: Programming Language :: Python :: 3.7
Classifier: Programming Language :: Python :: 3.8
Classifier: Programming Language :: Python :: 3.9
Requires-Dist: datasets (>=1.10.2,<2.0.0)
Requires-Dist: librosa (>=0.8.1,<0.9.0)
Requires-Dist: llvmlite (>=0.36.0,<0.37.0)
Requires-Dist: numba (>=0.53.1,<0.54.0)
Requires-Dist: torch (>=1.9.0,<2.0.0)
Requires-Dist: transformers (>=4.9.1,<5.0.0)
Project-URL: Documentation, https://github.com/jonatasgrosman/asrecognition
Project-URL: Repository, https://github.com/jonatasgrosman/asrecognition
Project-URL: issues, https://github.com/jonatasgrosman/asrecognition/issues
